README.md
setup.py
htc_api/__init__.py
htc_api/api.py
htc_api.egg-info/PKG-INFO
htc_api.egg-info/SOURCES.txt
htc_api.egg-info/dependency_links.txt
htc_api.egg-info/requires.txt
htc_api.egg-info/top_level.txt