Metadata-Version: 1.1
Name: htc_api
Version: 0.0.1
Summary: Hack The Classroom API
Home-page: https://github.com/hacktheclassroom/htc-api
Author: Spencer Hanson and Austin Jackson
Author-email: hacktheclassrooms@gmail.com
License: MIT
Platform: UNKNOWN
Classifier: Development Status :: 3 - Alpha
Classifier: Intended Audience :: Education
Classifier: Intended Audience :: Information Technology
Classifier: License :: OSI Approved :: MIT License
Classifier: Programming Language :: Python :: 3
Classifier: Programming Language :: Python :: 3.5
Classifier: Topic :: Security
